MSSpeechAPI4/MSSpeechAPI4.py
MSSpeechAPI4/__init__.py
msspeechapi4-0.0.1.dist-info/METADATA
msspeechapi4-0.0.1.dist-info/WHEEL
msspeechapi4-0.0.1.dist-info/licenses/LICENSE
msspeechapi4-0.0.1.dist-info/RECORD
