Metadata-Version: 2.3
Name: MSSpeechAPI4
Version: 0.0.1
Summary: My first package, which uses the Microsoft Speech API 4.0 to generate text to speech and play the sound files.
Project-URL: My_Github, https://github.com/Leaderofepic134
Author-email: Mossybee <i.got.your.tax.returns@gmail.com>
License-File: LICENSE
Classifier: License :: OSI Approved :: MIT License
Classifier: Operating System :: OS Independent
Classifier: Programming Language :: Python :: 3
Requires-Python: >=3.8
